geneplot.py
geneplot-1.0.0.dist-info/LICENSE
geneplot-1.0.0.dist-info/METADATA
geneplot-1.0.0.dist-info/WHEEL
geneplot-1.0.0.dist-info/top_level.txt
geneplot-1.0.0.dist-info/RECORD
