Metadata-Version: 2.1
Name: geneplot
Version: 1.0.0
Summary: Plot gene intron/exon topology, protein domains and SNPs
Home-page: https://github.com/gonzalezibeas/geneplot
Author: Daniel
Author-email: danielglz@mailfence.com
License: GPL
License-File: LICENSE
Requires-Dist: gffutils
Requires-Dist: Biopython
Requires-Dist: reportlab
Requires-Dist: matplotlib
